wdiff/.DS_Store
wdiff/__init__.py
wdiff/analyzer.py
wdiff/docsprocessor.py
wdiff/test-output.xml
wdiff/word.py
wdiff-0.0.9.dist-info/WHEEL
wdiff-0.0.9.dist-info/METADATA
wdiff-0.0.9.dist-info/RECORD
